stochoptim/__init__.py
stochoptim/util.py
stochoptim/scenclust/__init__.py
stochoptim/scenclust/cost_space_partition.py
stochoptim/scenclust/general_partitioning.py
stochoptim/scenclust/scenario_clustering.py
stochoptim/scengen/__init__.py
stochoptim/scengen/approx_prob.py
stochoptim/scengen/decision_process.py
stochoptim/scengen/figure_of_demerit.py
stochoptim/scengen/scenario_process.py
stochoptim/scengen/scenario_tree.py
stochoptim/scengen/temp.py
stochoptim/scengen/tree_search.py
stochoptim/scengen/tree_structure.py
stochoptim/scengen/variability_process.py
stochoptim/stochprob/__init__.py
stochoptim/stochprob/stochastic_problem_basis.py
stochoptim/stochprob/stochastic_solution_basis.py
stochoptim/stochprob/uncertainty_basis.py
stochoptim/stochprob/facility_location/__init__.py
stochoptim/stochprob/facility_location/facility_location_problem.py
stochoptim/stochprob/facility_location/facility_location_problem_multistage.py
stochoptim/stochprob/facility_location/facility_location_solution.py
stochoptim/stochprob/facility_location/facility_location_uncertainty.py
stochoptim/stochprob/network_design/__init__.py
stochoptim/stochprob/network_design/network_design_problem.py
stochoptim/stochprob/network_design/network_design_solution.py
stochoptim/stochprob/network_design/network_design_uncertainty.py
stochoptim-0.0.12.dist-info/LICENSE
stochoptim-0.0.12.dist-info/METADATA
stochoptim-0.0.12.dist-info/WHEEL
stochoptim-0.0.12.dist-info/top_level.txt
stochoptim-0.0.12.dist-info/RECORD
