Metadata-Version: 2.1
Name: stochoptim
Version: 0.0.12
Summary: StochOptim is a Stochastic Optimization package with scenario generation tools for two-stage and multi-stage problems
Home-page: https://github.com/julienkeutchayan/StochOptim
Author: Julien Keutchayan
Author-email: j.keutchayan@gmail.com
License: UNKNOWN
Platform: UNKNOWN
Classifier: Programming Language :: Python :: 3
Classifier: License :: OSI Approved :: MIT License
Classifier: Operating System :: OS Independent
Requires-Python: >=3.6
